{"187": {"p_init": 0.849582, "p_trans": 0.068609, "p_guess": 0.4999, "p_slip": 0.125074}, "374": {"p_init": 0.502106, "p_trans": 0.059156, "p_guess": 0.4999, "p_slip": 0.218585}, "188": {"p_init": 0.720504, "p_trans": 0.094731, "p_guess": 0.4999, "p_slip": 0.090476}, "168": {"p_init": 0.764292, "p_trans": 0.034102, "p_guess": 0.445755, "p_slip": 0.12197}, "172": {"p_init": 0.729524, "p_trans": 0.00146, "p_guess": 0.394428, "p_slip": 0.168527}, "200": {"p_init": 0.726948, "p_trans": 0.31764, "p_guess": 0.488753, "p_slip": 0.065689}, "240": {"p_init": 0.802289, "p_trans": 0.133989, "p_guess": 0.234234, "p_slip": 0.093381}, "132": {"p_init": 0.649181, "p_trans": 0.23637, "p_guess": 0.417276, "p_slip": 0.125731}, "402": {"p_init": 0.626101, "p_trans": 0.032349, "p_guess": 0.470951, "p_slip": 0.172106}, "352": {"p_init": 0.639316, "p_trans": 0.277116, "p_guess": 0.4999, "p_slip": 0.049254}, "208": {"p_init": 0.61533, "p_trans": 0.088052, "p_guess": 0.465634, "p_slip": 0.092196}, "2": {"p_init": 0.908685, "p_trans": 0.178773, "p_guess": 0.4999, "p_slip": 0.057586}, "243": {"p_init": 0.959082, "p_trans": 1e-06, "p_guess": 0.469796, "p_slip": 0.143325}, "5": {"p_init": 0.756054, "p_trans": 0.820019, "p_guess": 0.476549, "p_slip": 0.061059}, "313": {"p_init": 0.635548, "p_trans": 1e-06, "p_guess": 0.42139, "p_slip": 0.170146}, "11": {"p_init": 0.800872, "p_trans": 0.022219, "p_guess": 0.4999, "p_slip": 0.13798}, "6": {"p_init": 0.755866, "p_trans": 0.022899, "p_guess": 0.4999, "p_slip": 0.174231}, "140": {"p_init": 0.640071, "p_trans": 0.174958, "p_guess": 0.457854, "p_slip": 0.126446}, "7": {"p_init": 0.753468, "p_trans": 0.198684, "p_guess": 0.40281, "p_slip": 0.055437}, "18": {"p_init": 0.769287, "p_trans": 0.01922, "p_guess": 0.4999, "p_slip": 0.092059}, "373": {"p_init": 0.480055, "p_trans": 0.804965, "p_guess": 0.4999, "p_slip": 0.078119}, "12": {"p_init": 0.669553, "p_trans": 0.059542, "p_guess": 0.395717, "p_slip": 0.167413}, "10": {"p_init": 0.775967, "p_trans": 0.000249, "p_guess": 0.421904, "p_slip": 0.166018}, "16": {"p_init": 0.741483, "p_trans": 0.139629, "p_guess": 0.377174, "p_slip": 0.123912}, "13": {"p_init": 0.722277, "p_trans": 0.122002, "p_guess": 0.4999, "p_slip": 0.107098}, "20": {"p_init": 0.876044, "p_trans": 0.39092, "p_guess": 0.4999, "p_slip": 0.260688}, "14": {"p_init": 0.843517, "p_trans": 0.135097, "p_guess": 0.4999, "p_slip": 0.09786}, "22": {"p_init": 0.855882, "p_trans": 0.000931, "p_guess": 0.4999, "p_slip": 0.141709}, "25": {"p_init": 0.648387, "p_trans": 0.193316, "p_guess": 0.488334, "p_slip": 0.10537}, "24": {"p_init": 0.820098, "p_trans": 0.068794, "p_guess": 0.4999, "p_slip": 0.073278}, "73": {"p_init": 0.778395, "p_trans": 0.123758, "p_guess": 0.4999, "p_slip": 0.104576}, "30": {"p_init": 0.768898, "p_trans": 0.162173, "p_guess": 0.4999, "p_slip": 0.097055}, "34": {"p_init": 0.748285, "p_trans": 0.091422, "p_guess": 0.498466, "p_slip": 0.08423}, "248": {"p_init": 0.834258, "p_trans": 0.33698, "p_guess": 0.4999, "p_slip": 0.052854}, "162": {"p_init": 0.757486, "p_trans": 0.286663, "p_guess": 0.286137, "p_slip": 0.130296}, "38": {"p_init": 0.867994, "p_trans": 0.084043, "p_guess": 0.490316, "p_slip": 0.088342}, "35": {"p_init": 0.867011, "p_trans": 0.000604, "p_guess": 0.4999, "p_slip": 0.151909}, "33": {"p_init": 0.740572, "p_trans": 0.006013, "p_guess": 0.4999, "p_slip": 0.126425}, "32": {"p_init": 0.713297, "p_trans": 0.126483, "p_guess": 0.477783, "p_slip": 0.111958}, "37": {"p_init": 0.76494, "p_trans": 0.637007, "p_guess": 0.138862, "p_slip": 0.117586}, "253": {"p_init": 0.784503, "p_trans": 0.05239, "p_guess": 0.457616, "p_slip": 0.069514}, "546": {"p_init": 0.373824, "p_trans": 1e-06, "p_guess": 0.4999, "p_slip": 0.069427}, "40": {"p_init": 0.714665, "p_trans": 9.4e-05, "p_guess": 0.4999, "p_slip": 0.118173}, "41": {"p_init": 0.632713, "p_trans": 0.144001, "p_guess": 0.487005, "p_slip": 0.111351}, "311": {"p_init": 0.814684, "p_trans": 0.207915, "p_guess": 0.32664, "p_slip": 0.123396}, "46": {"p_init": 0.553547, "p_trans": 0.140478, "p_guess": 0.34965, "p_slip": 0.118011}, "42": {"p_init": 0.804809, "p_trans": 0.000823, "p_guess": 0.4999, "p_slip": 0.044958}, "55": {"p_init": 0.71357, "p_trans": 0.056869, "p_guess": 0.4999, "p_slip": 0.108918}, "47": {"p_init": 0.797077, "p_trans": 0.042444, "p_guess": 0.111346, "p_slip": 0.013086}, "69": {"p_init": 0.74566, "p_trans": 0.046392, "p_guess": 0.436099, "p_slip": 0.09668}, "157": {"p_init": 0.697842, "p_trans": 0.009856, "p_guess": 0.429309, "p_slip": 0.14004}, "57": {"p_init": 0.621811, "p_trans": 0.059315, "p_guess": 0.472544, "p_slip": 0.124681}, "64": {"p_init": 0.912687, "p_trans": 0.133192, "p_guess": 0.4999, "p_slip": 0.088517}, "102": {"p_init": 0.610577, "p_trans": 0.217676, "p_guess": 0.4999, "p_slip": 0.112403}, "147": {"p_init": 0.814589, "p_trans": 0.007307, "p_guess": 0.481643, "p_slip": 0.140902}, "78": {"p_init": 0.727063, "p_trans": 0.078282, "p_guess": 0.483315, "p_slip": 0.114652}, "378": {"p_init": 0.839871, "p_trans": 0.000163, "p_guess": 0.4999, "p_slip": 0.063324}, "104": {"p_init": 0.856931, "p_trans": 0.000113, "p_guess": 0.4999, "p_slip": 0.133949}, "277": {"p_init": 0.663938, "p_trans": 0.620276, "p_guess": 0.43349, "p_slip": 0.07203}, "99": {"p_init": 0.727701, "p_trans": 0.058132, "p_guess": 0.459548, "p_slip": 0.107907}, "116": {"p_init": 0.024429, "p_trans": 0.90003, "p_guess": 0.393446, "p_slip": 0.133014}, "114": {"p_init": 0.544471, "p_trans": 0.101522, "p_guess": 0.4999, "p_slip": 0.10734}, "112": {"p_init": 0.680348, "p_trans": 0.045847, "p_guess": 0.467604, "p_slip": 0.120094}, "118": {"p_init": 0.506992, "p_trans": 0.182597, "p_guess": 0.366797, "p_slip": 0.08649}, "129": {"p_init": 0.947535, "p_trans": 1e-06, "p_guess": 0.4999, "p_slip": 0.168885}, "282": {"p_init": 0.96101, "p_trans": 1e-06, "p_guess": 0.4999, "p_slip": 0.153301}, "131": {"p_init": 0.765924, "p_trans": 0.080559, "p_guess": 0.484901, "p_slip": 0.078601}, "134": {"p_init": 0.555712, "p_trans": 1e-06, "p_guess": 0.449942, "p_slip": 0.09018}, "173": {"p_init": 0.680601, "p_trans": 0.071844, "p_guess": 0.053042, "p_slip": 0.13592}, "138": {"p_init": 0.516516, "p_trans": 0.162074, "p_guess": 0.468804, "p_slip": 0.090764}, "9": {"p_init": 0.838024, "p_trans": 0.000566, "p_guess": 0.4999, "p_slip": 0.142148}, "231": {"p_init": 0.590078, "p_trans": 0.141661, "p_guess": 0.499109, "p_slip": 0.101418}, "65": {"p_init": 0.64455, "p_trans": 0.109407, "p_guess": 0.4999, "p_slip": 0.088587}, "62": {"p_init": 0.882694, "p_trans": 0.054133, "p_guess": 0.4999, "p_slip": 0.122907}, "148": {"p_init": 0.669055, "p_trans": 0.25831, "p_guess": 0.474637, "p_slip": 0.092515}, "155": {"p_init": 0.539773, "p_trans": 0.022533, "p_guess": 0.495711, "p_slip": 0.12048}, "109": {"p_init": 0.653729, "p_trans": 0.142952, "p_guess": 0.4999, "p_slip": 0.106868}, "320": {"p_init": 0.608541, "p_trans": 1e-05, "p_guess": 0.407133, "p_slip": 0.14584}, "166": {"p_init": 0.757098, "p_trans": 0.055427, "p_guess": 0.452748, "p_slip": 0.12529}, "77": {"p_init": 0.661838, "p_trans": 0.188724, "p_guess": 0.4999, "p_slip": 0.066536}, "81": {"p_init": 0.677323, "p_trans": 0.133645, "p_guess": 0.39786, "p_slip": 0.072729}, "339": {"p_init": 0.592311, "p_trans": 0.034885, "p_guess": 0.4999, "p_slip": 0.035306}, "336": {"p_init": 0.733997, "p_trans": 0.155757, "p_guess": 0.322115, "p_slip": 0.111607}, "626": {"p_init": 0.44124, "p_trans": 0.303307, "p_guess": 0.000688, "p_slip": 0.147961}, "56": {"p_init": 0.748778, "p_trans": 0.054429, "p_guess": 0.455715, "p_slip": 0.101173}, "58": {"p_init": 0.590914, "p_trans": 0.196036, "p_guess": 0.4999, "p_slip": 0.017691}, "681": {"p_init": 0.863372, "p_trans": 1e-06, "p_guess": 1e-06, "p_slip": 1e-06}, "340": {"p_init": 0.89701, "p_trans": 0.403506, "p_guess": 0.4999, "p_slip": 0.043213}, "193": {"p_init": 0.845148, "p_trans": 0.162752, "p_guess": 0.4999, "p_slip": 0.027222}, "204": {"p_init": 0.701016, "p_trans": 0.356314, "p_guess": 0.4999, "p_slip": 0.069839}, "413": {"p_init": 0.779597, "p_trans": 0.405871, "p_guess": 0.497677, "p_slip": 0.13144}, "343": {"p_init": 0.480739, "p_trans": 0.298715, "p_guess": 0.434592, "p_slip": 0.030553}, "327": {"p_init": 0.868874, "p_trans": 0.000544, "p_guess": 0.493556, "p_slip": 0.043757}, "786": {"p_init": 0.433735, "p_trans": 1e-06, "p_guess": 1e-06, "p_slip": 1e-06}, "198": {"p_init": 0.707472, "p_trans": 0.205115, "p_guess": 0.48238, "p_slip": 0.089884}, "241": {"p_init": 0.636464, "p_trans": 0.356214, "p_guess": 0.475775, "p_slip": 0.088746}, "67": {"p_init": 0.798759, "p_trans": 0.052287, "p_guess": 0.4999, "p_slip": 0.073214}, "43": {"p_init": 0.797517, "p_trans": 0.227469, "p_guess": 0.4999, "p_slip": 0.1342}, "349": {"p_init": 0.871811, "p_trans": 0.097278, "p_guess": 0.4999, "p_slip": 0.074589}, "612": {"p_init": 0.966461, "p_trans": 0.037633, "p_guess": 0.4999, "p_slip": 0.032633}, "252": {"p_init": 0.767547, "p_trans": 0.022157, "p_guess": 0.476285, "p_slip": 0.122974}, "206": {"p_init": 0.856623, "p_trans": 0.007126, "p_guess": 0.4999, "p_slip": 0.117222}, "212": {"p_init": 0.684036, "p_trans": 0.204152, "p_guess": 0.376482, "p_slip": 0.105408}, "214": {"p_init": 0.639273, "p_trans": 0.082477, "p_guess": 0.348813, "p_slip": 0.139232}, "23": {"p_init": 0.830398, "p_trans": 0.155629, "p_guess": 0.333633, "p_slip": 0.064689}, "359": {"p_init": 0.618784, "p_trans": 0.279217, "p_guess": 0.4999, "p_slip": 0.079162}, "180": {"p_init": 0.612153, "p_trans": 0.114237, "p_guess": 0.474559, "p_slip": 0.103321}, "223": {"p_init": 0.812061, "p_trans": 0.574784, "p_guess": 0.4999, "p_slip": 0.036876}, "222": {"p_init": 0.747381, "p_trans": 0.154523, "p_guess": 0.4999, "p_slip": 0.079932}, "361": {"p_init": 0.811904, "p_trans": 0.200778, "p_guess": 0.4999, "p_slip": 0.086286}, "362": {"p_init": 0.857823, "p_trans": 0.159526, "p_guess": 0.401173, "p_slip": 0.062967}, "91": {"p_init": 0.457794, "p_trans": 0.23172, "p_guess": 0.470429, "p_slip": 0.084758}, "266": {"p_init": 0.702915, "p_trans": 0.077711, "p_guess": 0.4999, "p_slip": 0.078828}, "307": {"p_init": 0.824951, "p_trans": 0.03452, "p_guess": 0.4999, "p_slip": 0.158154}, "108": {"p_init": 0.82858, "p_trans": 0.212255, "p_guess": 0.4999, "p_slip": 0.141813}, "161": {"p_init": 0.612889, "p_trans": 0.181664, "p_guess": 0.384459, "p_slip": 0.1847}, "36": {"p_init": 0.837114, "p_trans": 0.292282, "p_guess": 0.161821, "p_slip": 0.094266}, "179": {"p_init": 0.735511, "p_trans": 0.166181, "p_guess": 0.337754, "p_slip": 0.130577}, "169": {"p_init": 0.660644, "p_trans": 0.313183, "p_guess": 0.4999, "p_slip": 0.115248}, "176": {"p_init": 0.41192, "p_trans": 0.477646, "p_guess": 0.391076, "p_slip": 0.139237}, "177": {"p_init": 0.689306, "p_trans": 0.157119, "p_guess": 0.459434, "p_slip": 0.090062}, "178": {"p_init": 0.535528, "p_trans": 0.653179, "p_guess": 0.4999, "p_slip": 0.041377}, "183": {"p_init": 0.543397, "p_trans": 0.133142, "p_guess": 0.498805, "p_slip": 0.078941}, "182": {"p_init": 0.669377, "p_trans": 0.419186, "p_guess": 0.4999, "p_slip": 0.164276}, "181": {"p_init": 0.132356, "p_trans": 0.707983, "p_guess": 0.455785, "p_slip": 0.120207}, "330": {"p_init": 0.743586, "p_trans": 0.246763, "p_guess": 0.363929, "p_slip": 0.106616}, "76": {"p_init": 0.78317, "p_trans": 0.095165, "p_guess": 0.492128, "p_slip": 0.053295}, "335": {"p_init": 0.623573, "p_trans": 0.187387, "p_guess": 0.470121, "p_slip": 0.109495}, "341": {"p_init": 0.857335, "p_trans": 0.824821, "p_guess": 0.4999, "p_slip": 0.014709}, "342": {"p_init": 0.857335, "p_trans": 0.824821, "p_guess": 0.4999, "p_slip": 0.014709}, "205": {"p_init": 0.850045, "p_trans": 0.339726, "p_guess": 0.441716, "p_slip": 0.073638}, "207": {"p_init": 0.720201, "p_trans": 0.308681, "p_guess": 0.497874, "p_slip": 0.040452}, "209": {"p_init": 0.619247, "p_trans": 0.139322, "p_guess": 0.4999, "p_slip": 0.142411}, "66": {"p_init": 0.822527, "p_trans": 0.631448, "p_guess": 0.4999, "p_slip": 0.105262}, "390": {"p_init": 0.821863, "p_trans": 0.789504, "p_guess": 0.4999, "p_slip": 0.014178}, "220": {"p_init": 0.822918, "p_trans": 0.106293, "p_guess": 0.4999, "p_slip": 0.081031}, "392": {"p_init": 0.886442, "p_trans": 0.812237, "p_guess": 0.4999, "p_slip": 0.007482}, "301": {"p_init": 0.794201, "p_trans": 0.559528, "p_guess": 0.4999, "p_slip": 0.021749}, "363": {"p_init": 0.867219, "p_trans": 0.129588, "p_guess": 0.4999, "p_slip": 0.06724}, "365": {"p_init": 0.837997, "p_trans": 0.586412, "p_guess": 0.4999, "p_slip": 0.129207}, "366": {"p_init": 0.993655, "p_trans": 0.00046, "p_guess": 0.4999, "p_slip": 0.019878}, "139": {"p_init": 0.832872, "p_trans": 0.112046, "p_guess": 0.4999, "p_slip": 0.097649}, "142": {"p_init": 0.696333, "p_trans": 0.094368, "p_guess": 0.4999, "p_slip": 0.168669}, "144": {"p_init": 0.412928, "p_trans": 0.165491, "p_guess": 0.459933, "p_slip": 0.059587}, "146": {"p_init": 0.746218, "p_trans": 0.001203, "p_guess": 0.45998, "p_slip": 0.094416}, "232": {"p_init": 0.432429, "p_trans": 0.120398, "p_guess": 0.47114, "p_slip": 0.122788}, "119": {"p_init": 0.789131, "p_trans": 0.130795, "p_guess": 0.4999, "p_slip": 0.080592}, "31": {"p_init": 0.868312, "p_trans": 0.185073, "p_guess": 0.330652, "p_slip": 0.053176}, "272": {"p_init": 0.845777, "p_trans": 0.104017, "p_guess": 0.425906, "p_slip": 0.134724}, "149": {"p_init": 0.709267, "p_trans": 0.35934, "p_guess": 0.330045, "p_slip": 0.122476}, "150": {"p_init": 0.422112, "p_trans": 0.279136, "p_guess": 0.431932, "p_slip": 0.153249}, "151": {"p_init": 0.299458, "p_trans": 0.685789, "p_guess": 0.33697, "p_slip": 0.040166}, "154": {"p_init": 0.582256, "p_trans": 0.340178, "p_guess": 0.4999, "p_slip": 0.095824}, "389": {"p_init": 0.789721, "p_trans": 6e-05, "p_guess": 0.4999, "p_slip": 0.078202}, "51": {"p_init": 0.529415, "p_trans": 0.70268, "p_guess": 0.4999, "p_slip": 0.045857}, "470": {"p_init": 0.782302, "p_trans": 0.357154, "p_guess": 0.144539, "p_slip": 0.014835}, "54": {"p_init": 0.741846, "p_trans": 0.277622, "p_guess": 0.4999, "p_slip": 0.066295}, "160": {"p_init": 0.863747, "p_trans": 0.080281, "p_guess": 0.4999, "p_slip": 0.074784}, "106": {"p_init": 0.890283, "p_trans": 0.109351, "p_guess": 0.4999, "p_slip": 0.057035}, "237": {"p_init": 0.678693, "p_trans": 0.200124, "p_guess": 0.45541, "p_slip": 0.082923}, "121": {"p_init": 0.866651, "p_trans": 0.01753, "p_guess": 0.458717, "p_slip": 0.097912}, "164": {"p_init": 0.711878, "p_trans": 0.202651, "p_guess": 0.4999, "p_slip": 0.073223}, "165": {"p_init": 0.781241, "p_trans": 0.077316, "p_guess": 0.356002, "p_slip": 0.079085}, "203": {"p_init": 0.770626, "p_trans": 0.101648, "p_guess": 0.449725, "p_slip": 0.119669}, "184": {"p_init": 0.710357, "p_trans": 0.619179, "p_guess": 0.4999, "p_slip": 0.130181}, "329": {"p_init": 0.860117, "p_trans": 0.190266, "p_guess": 0.302699, "p_slip": 0.076809}, "170": {"p_init": 0.770409, "p_trans": 0.141668, "p_guess": 0.373732, "p_slip": 0.152529}, "468": {"p_init": 0.718422, "p_trans": 0.245772, "p_guess": 0.346457, "p_slip": 0.078014}, "133": {"p_init": 0.606718, "p_trans": 0.526765, "p_guess": 0.425528, "p_slip": 0.087996}, "202": {"p_init": 0.806276, "p_trans": 0.314961, "p_guess": 0.445697, "p_slip": 0.053375}, "213": {"p_init": 0.457999, "p_trans": 0.307252, "p_guess": 0.369758, "p_slip": 0.150177}, "238": {"p_init": 0.69027, "p_trans": 0.197788, "p_guess": 0.468096, "p_slip": 0.109029}, "88": {"p_init": 0.558476, "p_trans": 0.170254, "p_guess": 0.486122, "p_slip": 0.055654}, "227": {"p_init": 0.882472, "p_trans": 0.207379, "p_guess": 0.4999, "p_slip": 0.04051}, "225": {"p_init": 0.63225, "p_trans": 0.429703, "p_guess": 0.4999, "p_slip": 0.141496}, "244": {"p_init": 0.621579, "p_trans": 0.596517, "p_guess": 0.4165, "p_slip": 0.028609}, "477": {"p_init": 0.601386, "p_trans": 1e-06, "p_guess": 0.436386, "p_slip": 0.165352}, "478": {"p_init": 0.602638, "p_trans": 1e-06, "p_guess": 0.426088, "p_slip": 0.165384}, "3": {"p_init": 0.714468, "p_trans": 1e-06, "p_guess": 0.473385, "p_slip": 0.165268}, "448": {"p_init": 0.915276, "p_trans": 0.000364, "p_guess": 0.4999, "p_slip": 0.123854}, "249": {"p_init": 0.83505, "p_trans": 0.001421, "p_guess": 0.377938, "p_slip": 0.144633}, "250": {"p_init": 0.733046, "p_trans": 0.456193, "p_guess": 0.46066, "p_slip": 0.038848}, "68": {"p_init": 0.987331, "p_trans": 0.151056, "p_guess": 0.242294, "p_slip": 0.021319}, "257": {"p_init": 0.787957, "p_trans": 0.000257, "p_guess": 0.4999, "p_slip": 0.152584}, "258": {"p_init": 0.694302, "p_trans": 7.4e-05, "p_guess": 0.4999, "p_slip": 0.154479}, "260": {"p_init": 0.77141, "p_trans": 1e-05, "p_guess": 0.46619, "p_slip": 0.115274}, "261": {"p_init": 0.836281, "p_trans": 2.4e-05, "p_guess": 0.424566, "p_slip": 0.192922}, "262": {"p_init": 0.918795, "p_trans": 0.001409, "p_guess": 0.4999, "p_slip": 0.11108}, "263": {"p_init": 0.870889, "p_trans": 0.024894, "p_guess": 0.4999, "p_slip": 0.130872}, "264": {"p_init": 0.803177, "p_trans": 5.1e-05, "p_guess": 0.4999, "p_slip": 0.1585}, "435": {"p_init": 0.880152, "p_trans": 0.010378, "p_guess": 0.335198, "p_slip": 0.08611}, "59": {"p_init": 0.745476, "p_trans": 0.360857, "p_guess": 0.278175, "p_slip": 0.053821}, "480": {"p_init": 0.452262, "p_trans": 9.3e-05, "p_guess": 0.472343, "p_slip": 0.127824}, "61": {"p_init": 0.779543, "p_trans": 0.001155, "p_guess": 0.443389, "p_slip": 0.114564}, "271": {"p_init": 0.884149, "p_trans": 0.171842, "p_guess": 0.4999, "p_slip": 0.088184}, "462": {"p_init": 0.29417, "p_trans": 0.170942, "p_guess": 0.402397, "p_slip": 0.164705}, "117": {"p_init": 0.819541, "p_trans": 0.001222, "p_guess": 0.385231, "p_slip": 0.101041}, "242": {"p_init": 0.788415, "p_trans": 0.057494, "p_guess": 0.269769, "p_slip": 0.159892}, "408": {"p_init": 0.485428, "p_trans": 0.172495, "p_guess": 0.091411, "p_slip": 0.128172}, "82": {"p_init": 0.605557, "p_trans": 0.115587, "p_guess": 0.4999, "p_slip": 0.112276}, "101": {"p_init": 0.701584, "p_trans": 1e-06, "p_guess": 0.4999, "p_slip": 0.187625}, "283": {"p_init": 0.894938, "p_trans": 7e-06, "p_guess": 0.4999, "p_slip": 0.218179}, "409": {"p_init": 0.562488, "p_trans": 0.029752, "p_guess": 0.398474, "p_slip": 0.035531}, "410": {"p_init": 0.559707, "p_trans": 0.028553, "p_guess": 0.398225, "p_slip": 0.033582}, "411": {"p_init": 0.564773, "p_trans": 0.025792, "p_guess": 0.396223, "p_slip": 0.036201}, "115": {"p_init": 0.564386, "p_trans": 0.025996, "p_guess": 0.396357, "p_slip": 0.035936}, "412": {"p_init": 0.559707, "p_trans": 0.028553, "p_guess": 0.398225, "p_slip": 0.033582}, "123": {"p_init": 0.684568, "p_trans": 0.010661, "p_guess": 0.4999, "p_slip": 0.163711}, "124": {"p_init": 0.616694, "p_trans": 0.062368, "p_guess": 0.439257, "p_slip": 0.147866}, "127": {"p_init": 0.815473, "p_trans": 0.024768, "p_guess": 0.454613, "p_slip": 0.190431}, "422": {"p_init": 0.879134, "p_trans": 0.002171, "p_guess": 0.4999, "p_slip": 0.097141}, "291": {"p_init": 0.555002, "p_trans": 0.018018, "p_guess": 0.4999, "p_slip": 0.330946}, "128": {"p_init": 0.632682, "p_trans": 4e-06, "p_guess": 0.484216, "p_slip": 0.203197}, "130": {"p_init": 0.555809, "p_trans": 0.063535, "p_guess": 0.436813, "p_slip": 0.088942}, "292": {"p_init": 0.412453, "p_trans": 0.919274, "p_guess": 0.319465, "p_slip": 0.037376}, "135": {"p_init": 0.843992, "p_trans": 1e-06, "p_guess": 0.424114, "p_slip": 0.163802}, "294": {"p_init": 0.592356, "p_trans": 1e-06, "p_guess": 0.38443, "p_slip": 0.272726}, "167": {"p_init": 0.86311, "p_trans": 0.00833, "p_guess": 0.4999, "p_slip": 0.210637}, "486": {"p_init": 0.839465, "p_trans": 0.002853, "p_guess": 0.487589, "p_slip": 0.082956}, "145": {"p_init": 0.429195, "p_trans": 0.206775, "p_guess": 0.419384, "p_slip": 0.065357}, "497": {"p_init": 0.259297, "p_trans": 0.003772, "p_guess": 0.12521, "p_slip": 0.109588}, "488": {"p_init": 0.26964, "p_trans": 0.699231, "p_guess": 0.064217, "p_slip": 0.057823}, "308": {"p_init": 0.761044, "p_trans": 3e-06, "p_guess": 0.4999, "p_slip": 0.091166}, "39": {"p_init": 0.744804, "p_trans": 0.26396, "p_guess": 0.4999, "p_slip": 0.123086}, "152": {"p_init": 0.576198, "p_trans": 0.587388, "p_guess": 0.261687, "p_slip": 0.0874}, "8": {"p_init": 0.894109, "p_trans": 0.195931, "p_guess": 0.499895, "p_slip": 0.085993}, "303": {"p_init": 0.432903, "p_trans": 0.006062, "p_guess": 0.392258, "p_slip": 0.166331}, "26": {"p_init": 0.608047, "p_trans": 0.188638, "p_guess": 0.48835, "p_slip": 0.071506}, "326": {"p_init": 0.743363, "p_trans": 0.660653, "p_guess": 0.4999, "p_slip": 0.130698}, "175": {"p_init": 0.863852, "p_trans": 0.215198, "p_guess": 0.198138, "p_slip": 0.068118}, "194": {"p_init": 0.739528, "p_trans": 0.915271, "p_guess": 0.4999, "p_slip": 0.129934}, "192": {"p_init": 0.951129, "p_trans": 0.087116, "p_guess": 0.4999, "p_slip": 0.054619}, "239": {"p_init": 0.722985, "p_trans": 0.259064, "p_guess": 0.48414, "p_slip": 0.041368}, "199": {"p_init": 0.774938, "p_trans": 0.426347, "p_guess": 0.4999, "p_slip": 0.063888}, "105": {"p_init": 0.641578, "p_trans": 0.000166, "p_guess": 0.4999, "p_slip": 0.095562}, "221": {"p_init": 0.634443, "p_trans": 0.150632, "p_guess": 0.44986, "p_slip": 0.097419}, "211": {"p_init": 0.813887, "p_trans": 0.365442, "p_guess": 0.468254, "p_slip": 0.002527}, "360": {"p_init": 0.756252, "p_trans": 0.723806, "p_guess": 0.4999, "p_slip": 0.059199}, "87": {"p_init": 0.477151, "p_trans": 0.768573, "p_guess": 0.4999, "p_slip": 0.156571}, "371": {"p_init": 0.875606, "p_trans": 3e-06, "p_guess": 0.4999, "p_slip": 0.230323}, "351": {"p_init": 0.821422, "p_trans": 0.625769, "p_guess": 0.437881, "p_slip": 0.001597}, "218": {"p_init": 0.270608, "p_trans": 0.655441, "p_guess": 0.394125, "p_slip": 0.053844}, "367": {"p_init": 0.718279, "p_trans": 2e-06, "p_guess": 0.4999, "p_slip": 0.161051}, "289": {"p_init": 0.591187, "p_trans": 0.626446, "p_guess": 0.4999, "p_slip": 0.032099}, "508": {"p_init": 0.988412, "p_trans": 0.000142, "p_guess": 1e-06, "p_slip": 0.122423}, "510": {"p_init": 0.878464, "p_trans": 0.001096, "p_guess": 0.4999, "p_slip": 0.17472}, "511": {"p_init": 0.967312, "p_trans": 0.988627, "p_guess": 0.4999, "p_slip": 0.19653}, "368": {"p_init": 0.894626, "p_trans": 0.334541, "p_guess": 0.266241, "p_slip": 0.033345}, "74": {"p_init": 0.386899, "p_trans": 0.36913, "p_guess": 0.309868, "p_slip": 0.058841}, "512": {"p_init": 0.956079, "p_trans": 0.011274, "p_guess": 0.4999, "p_slip": 0.032827}, "535": {"p_init": 0.818585, "p_trans": 0.006167, "p_guess": 0.4999, "p_slip": 0.048683}, "524": {"p_init": 0.434843, "p_trans": 0.666833, "p_guess": 0.469336, "p_slip": 0.013121}, "382": {"p_init": 0.813062, "p_trans": 0.044391, "p_guess": 0.248133, "p_slip": 0.168819}, "526": {"p_init": 0.987585, "p_trans": 0.002338, "p_guess": 0.4999, "p_slip": 0.0001}, "28": {"p_init": 0.893373, "p_trans": 0.068692, "p_guess": 0.224647, "p_slip": 0.04162}, "550": {"p_init": 0.910069, "p_trans": 0.986983, "p_guess": 0.4999, "p_slip": 0.166474}, "554": {"p_init": 0.896172, "p_trans": 0.35337, "p_guess": 0.267747, "p_slip": 0.070977}, "553": {"p_init": 0.856463, "p_trans": 0.022334, "p_guess": 0.4999, "p_slip": 0.00974}, "141": {"p_init": 0.673725, "p_trans": 0.605819, "p_guess": 0.4999, "p_slip": 0.061391}, "143": {"p_init": 0.947121, "p_trans": 0.500782, "p_guess": 0.4999, "p_slip": 0.00206}, "317": {"p_init": 0.971929, "p_trans": 0.245496, "p_guess": 0.4999, "p_slip": 0.0743}, "153": {"p_init": 0.481037, "p_trans": 0.857621, "p_guess": 0.302382, "p_slip": 0.050595}, "163": {"p_init": 0.216257, "p_trans": 0.386109, "p_guess": 0.421195, "p_slip": 0.10844}, "379": {"p_init": 0.823115, "p_trans": 0.038255, "p_guess": 0.418749, "p_slip": 0.044989}, "210": {"p_init": 0.159109, "p_trans": 0.622226, "p_guess": 0.372903, "p_slip": 0.106481}, "195": {"p_init": 0.956236, "p_trans": 0.66578, "p_guess": 0.4999, "p_slip": 0.016748}, "201": {"p_init": 0.600391, "p_trans": 0.686176, "p_guess": 0.323978, "p_slip": 0.019775}, "217": {"p_init": 0.504699, "p_trans": 0.246682, "p_guess": 0.4999, "p_slip": 0.171405}, "228": {"p_init": 0.591969, "p_trans": 1e-05, "p_guess": 0.4999, "p_slip": 0.279153}, "229": {"p_init": 0.392359, "p_trans": 0.023844, "p_guess": 0.354623, "p_slip": 0.181541}, "233": {"p_init": 0.853023, "p_trans": 1e-06, "p_guess": 0.46713, "p_slip": 0.071556}, "234": {"p_init": 0.839147, "p_trans": 3e-06, "p_guess": 0.439516, "p_slip": 0.074827}, "235": {"p_init": 0.851732, "p_trans": 1e-06, "p_guess": 0.467647, "p_slip": 0.071189}, "236": {"p_init": 0.553107, "p_trans": 0.224299, "p_guess": 0.367613, "p_slip": 0.102774}, "401": {"p_init": 0.581653, "p_trans": 0.153184, "p_guess": 0.430212, "p_slip": 0.082301}, "487": {"p_init": 0.795033, "p_trans": 0.387689, "p_guess": 0.087637, "p_slip": 0.091192}, "86": {"p_init": 0.60858, "p_trans": 0.114553, "p_guess": 0.409232, "p_slip": 0.137196}, "98": {"p_init": 0.636868, "p_trans": 0.431104, "p_guess": 0.495066, "p_slip": 0.135751}, "284": {"p_init": 0.831351, "p_trans": 0.001145, "p_guess": 0.48202, "p_slip": 0.107118}, "285": {"p_init": 0.795465, "p_trans": 0.000136, "p_guess": 0.4999, "p_slip": 0.192936}, "286": {"p_init": 0.900081, "p_trans": 0.877733, "p_guess": 0.4999, "p_slip": 0.092775}, "322": {"p_init": 0.63155, "p_trans": 0.551003, "p_guess": 0.4999, "p_slip": 0.053257}, "304": {"p_init": 0.704925, "p_trans": 0.377248, "p_guess": 0.4999, "p_slip": 0.092045}, "0": {"p_init": 0.410825, "p_trans": 1e-06, "p_guess": 0.4999, "p_slip": 0.206871}, "288": {"p_init": 0.548675, "p_trans": 2.1e-05, "p_guess": 0.478733, "p_slip": 0.035873}, "122": {"p_init": 0.808278, "p_trans": 0.017678, "p_guess": 0.482816, "p_slip": 0.093023}, "414": {"p_init": 0.930155, "p_trans": 0.000152, "p_guess": 0.4999, "p_slip": 0.312467}, "137": {"p_init": 0.799018, "p_trans": 0.250914, "p_guess": 0.44846, "p_slip": 0.051349}, "216": {"p_init": 0.44806, "p_trans": 0.000171, "p_guess": 0.404458, "p_slip": 0.082067}, "259": {"p_init": 0.668007, "p_trans": 7e-06, "p_guess": 0.4999, "p_slip": 0.347239}, "265": {"p_init": 0.794223, "p_trans": 0.328737, "p_guess": 0.492868, "p_slip": 0.048392}, "447": {"p_init": 0.934602, "p_trans": 0.254961, "p_guess": 0.4999, "p_slip": 0.021451}, "92": {"p_init": 0.757926, "p_trans": 0.349573, "p_guess": 0.4999, "p_slip": 0.088323}, "405": {"p_init": 0.787959, "p_trans": 0.167598, "p_guess": 0.407946, "p_slip": 0.029994}, "256": {"p_init": 0.9999, "p_trans": 0.9999, "p_guess": 0.4999, "p_slip": 1e-06}, "407": {"p_init": 0.556336, "p_trans": 7.8e-05, "p_guess": 0.476354, "p_slip": 0.118553}, "174": {"p_init": 0.847314, "p_trans": 0.03591, "p_guess": 0.379592, "p_slip": 0.115401}, "79": {"p_init": 0.791468, "p_trans": 0.312423, "p_guess": 0.496534, "p_slip": 0.080122}, "100": {"p_init": 0.710473, "p_trans": 0.20641, "p_guess": 0.242768, "p_slip": 0.149349}, "107": {"p_init": 0.751987, "p_trans": 1.7e-05, "p_guess": 0.459056, "p_slip": 0.13702}, "469": {"p_init": 0.897504, "p_trans": 0.642646, "p_guess": 0.4999, "p_slip": 0.023475}, "485": {"p_init": 0.815666, "p_trans": 0.999764, "p_guess": 0.4999, "p_slip": 0.023233}, "471": {"p_init": 0.835814, "p_trans": 0.463683, "p_guess": 0.135644, "p_slip": 0.021573}, "380": {"p_init": 0.154149, "p_trans": 0.46717, "p_guess": 0.33307, "p_slip": 0.068774}, "29": {"p_init": 0.725762, "p_trans": 0.181674, "p_guess": 0.4999, "p_slip": 0.078733}, "19": {"p_init": 0.741363, "p_trans": 0.329448, "p_guess": 0.4999, "p_slip": 0.195435}, "113": {"p_init": 0.894397, "p_trans": 0.999874, "p_guess": 0.4999, "p_slip": 0.05807}, "120": {"p_init": 0.652374, "p_trans": 0.230489, "p_guess": 0.324167, "p_slip": 0.044342}, "136": {"p_init": 0.603634, "p_trans": 0.000167, "p_guess": 0.407539, "p_slip": 0.03125}, "321": {"p_init": 0.573685, "p_trans": 0.025306, "p_guess": 0.434471, "p_slip": 0.0624}, "325": {"p_init": 0.321055, "p_trans": 0.010218, "p_guess": 0.434602, "p_slip": 0.031693}, "196": {"p_init": 0.699926, "p_trans": 0.983044, "p_guess": 0.4999, "p_slip": 0.106853}, "125": {"p_init": 0.77911, "p_trans": 0.034987, "p_guess": 0.4999, "p_slip": 0.210953}, "394": {"p_init": 0.272149, "p_trans": 0.533953, "p_guess": 0.294418, "p_slip": 0.100062}, "171": {"p_init": 0.414499, "p_trans": 0.776729, "p_guess": 0.451529, "p_slip": 0.028533}, "337": {"p_init": 0.374984, "p_trans": 0.602733, "p_guess": 0.30785, "p_slip": 0.020597}, "44": {"p_init": 0.467046, "p_trans": 0.195454, "p_guess": 0.499646, "p_slip": 0.128006}, "96": {"p_init": 0.958435, "p_trans": 1e-06, "p_guess": 0.4999, "p_slip": 0.12552}, "224": {"p_init": 0.769027, "p_trans": 0.684204, "p_guess": 0.4999, "p_slip": 0.027869}, "189": {"p_init": 0.916335, "p_trans": 0.43282, "p_guess": 0.49155, "p_slip": 0.046836}, "643": {"p_init": 0.822276, "p_trans": 0.0478, "p_guess": 0.4999, "p_slip": 0.098817}, "644": {"p_init": 0.412192, "p_trans": 0.50777, "p_guess": 0.347884, "p_slip": 0.029539}, "635": {"p_init": 0.642423, "p_trans": 0.098683, "p_guess": 0.4991, "p_slip": 1e-05}, "586": {"p_init": 0.631422, "p_trans": 0.114565, "p_guess": 0.474531, "p_slip": 1.1e-05}, "659": {"p_init": 0.983854, "p_trans": 7.1e-05, "p_guess": 0.119926, "p_slip": 0.052434}, "376": {"p_init": 0.983831, "p_trans": 0.000108, "p_guess": 0.121407, "p_slip": 0.052876}, "276": {"p_init": 0.70383, "p_trans": 0.469054, "p_guess": 0.450668, "p_slip": 0.02845}, "80": {"p_init": 0.816569, "p_trans": 0.117525, "p_guess": 0.4999, "p_slip": 0.089636}, "275": {"p_init": 0.968462, "p_trans": 0.988501, "p_guess": 0.4999, "p_slip": 0.119464}, "83": {"p_init": 0.526772, "p_trans": 0.316716, "p_guess": 0.372915, "p_slip": 0.141297}, "580": {"p_init": 0.809338, "p_trans": 0.000248, "p_guess": 0.492903, "p_slip": 0.110834}, "431": {"p_init": 0.757394, "p_trans": 0.153425, "p_guess": 0.4999, "p_slip": 0.112943}, "85": {"p_init": 0.619643, "p_trans": 0.121399, "p_guess": 0.179175, "p_slip": 0.11949}, "296": {"p_init": 0.41823, "p_trans": 0.021737, "p_guess": 0.4999, "p_slip": 0.156166}, "582": {"p_init": 0.931177, "p_trans": 9.6e-05, "p_guess": 0.4999, "p_slip": 0.061831}, "463": {"p_init": 0.893324, "p_trans": 0.004201, "p_guess": 0.4999, "p_slip": 0.00274}, "230": {"p_init": 0.525635, "p_trans": 0.358479, "p_guess": 0.349488, "p_slip": 0.046501}, "72": {"p_init": 0.860105, "p_trans": 0.004025, "p_guess": 0.4999, "p_slip": 0.104589}, "624": {"p_init": 0.864811, "p_trans": 0.003772, "p_guess": 0.4999, "p_slip": 0.123831}, "93": {"p_init": 0.785056, "p_trans": 0.000174, "p_guess": 0.4999, "p_slip": 0.097661}, "103": {"p_init": 0.666247, "p_trans": 0.196608, "p_guess": 0.368742, "p_slip": 0.072321}, "270": {"p_init": 0.295015, "p_trans": 1e-06, "p_guess": 0.401883, "p_slip": 0.179559}, "219": {"p_init": 0.325098, "p_trans": 0.620678, "p_guess": 0.409998, "p_slip": 0.050252}, "226": {"p_init": 0.608389, "p_trans": 0.852774, "p_guess": 0.454517, "p_slip": 0.018433}, "246": {"p_init": 0.768291, "p_trans": 0.449996, "p_guess": 0.495871, "p_slip": 0.059255}, "318": {"p_init": 0.997589, "p_trans": 0.99926, "p_guess": 0.4999, "p_slip": 0.104215}, "507": {"p_init": 0.728051, "p_trans": 0.56108, "p_guess": 0.466786, "p_slip": 0.006053}, "372": {"p_init": 0.806738, "p_trans": 0.250999, "p_guess": 0.4999, "p_slip": 0.097185}, "509": {"p_init": 0.59652, "p_trans": 0.719624, "p_guess": 0.449291, "p_slip": 0.011262}, "185": {"p_init": 0.571961, "p_trans": 0.791143, "p_guess": 0.361943, "p_slip": 0.060855}, "571": {"p_init": 0.905928, "p_trans": 0.9999, "p_guess": 0.4999, "p_slip": 0.09414}, "518": {"p_init": 0.796618, "p_trans": 0.684567, "p_guess": 0.4999, "p_slip": 0.105983}, "541": {"p_init": 0.987972, "p_trans": 0.9999, "p_guess": 0.4999, "p_slip": 0.098984}, "110": {"p_init": 0.624403, "p_trans": 0.504099, "p_guess": 0.4999, "p_slip": 0.064268}, "536": {"p_init": 0.944073, "p_trans": 0.105184, "p_guess": 0.396433, "p_slip": 0.112259}, "634": {"p_init": 0.515022, "p_trans": 0.011007, "p_guess": 0.480527, "p_slip": 0.073239}, "540": {"p_init": 0.769401, "p_trans": 0.30665, "p_guess": 0.358292, "p_slip": 0.000276}, "156": {"p_init": 0.77438, "p_trans": 3.4e-05, "p_guess": 0.437746, "p_slip": 3e-06}, "191": {"p_init": 0.852906, "p_trans": 0.999795, "p_guess": 0.4999, "p_slip": 0.014269}, "381": {"p_init": 0.828325, "p_trans": 0.060986, "p_guess": 0.4999, "p_slip": 0.057217}, "386": {"p_init": 0.900707, "p_trans": 1e-06, "p_guess": 0.4999, "p_slip": 0.043318}, "306": {"p_init": 0.373389, "p_trans": 0.12562, "p_guess": 0.283524, "p_slip": 6.9e-05}, "345": {"p_init": 0.373899, "p_trans": 0.012766, "p_guess": 0.329641, "p_slip": 0.122842}, "655": {"p_init": 0.420455, "p_trans": 1e-06, "p_guess": 1e-06, "p_slip": 1e-06}, "63": {"p_init": 0.662593, "p_trans": 0.707662, "p_guess": 0.499602, "p_slip": 0.014295}, "190": {"p_init": 0.593609, "p_trans": 0.581106, "p_guess": 0.42796, "p_slip": 0.02182}, "501": {"p_init": 0.959169, "p_trans": 0.075366, "p_guess": 0.4999, "p_slip": 0.026352}, "53": {"p_init": 0.864407, "p_trans": 1e-06, "p_guess": 0.4999, "p_slip": 0.310576}, "466": {"p_init": 0.622611, "p_trans": 1e-06, "p_guess": 0.4999, "p_slip": 0.215887}, "71": {"p_init": 0.992915, "p_trans": 1e-06, "p_guess": 0.4999, "p_slip": 0.186784}, "279": {"p_init": 0.808244, "p_trans": 0.193649, "p_guess": 0.246995, "p_slip": 0.062377}, "396": {"p_init": 0.972773, "p_trans": 0.005387, "p_guess": 0.130748, "p_slip": 0.164475}, "97": {"p_init": 0.952057, "p_trans": 1e-06, "p_guess": 0.083195, "p_slip": 1e-06}, "300": {"p_init": 0.261421, "p_trans": 0.921396, "p_guess": 0.367354, "p_slip": 0.015471}, "280": {"p_init": 0.728723, "p_trans": 0.345352, "p_guess": 0.354552, "p_slip": 0.055567}, "446": {"p_init": 0.541295, "p_trans": 0.474056, "p_guess": 0.4999, "p_slip": 0.294662}, "197": {"p_init": 0.308729, "p_trans": 0.357157, "p_guess": 0.227295, "p_slip": 0.036522}, "420": {"p_init": 0.633165, "p_trans": 0.443051, "p_guess": 0.49758, "p_slip": 0.162725}, "513": {"p_init": 0.735469, "p_trans": 0.421899, "p_guess": 0.4999, "p_slip": 0.072589}, "388": {"p_init": 0.437513, "p_trans": 0.099612, "p_guess": 0.298515, "p_slip": 0.308004}, "647": {"p_init": 0.856121, "p_trans": 0.010659, "p_guess": 0.4999, "p_slip": 0.106505}, "649": {"p_init": 0.532061, "p_trans": 0.461319, "p_guess": 0.412995, "p_slip": 0.070109}, "650": {"p_init": 0.532061, "p_trans": 0.461319, "p_guess": 0.412995, "p_slip": 0.070109}, "660": {"p_init": 0.809749, "p_trans": 0.442275, "p_guess": 0.423693, "p_slip": 0.027102}, "588": {"p_init": 0.934785, "p_trans": 0.9999, "p_guess": 0.477297, "p_slip": 1e-06}, "587": {"p_init": 0.970765, "p_trans": 0.999123, "p_guess": 0.4999, "p_slip": 0.026772}, "589": {"p_init": 0.60061, "p_trans": 0.62029, "p_guess": 0.190184, "p_slip": 0.002593}, "15": {"p_init": 0.838472, "p_trans": 0.847381, "p_guess": 0.4999, "p_slip": 0.143194}, "562": {"p_init": 0.634799, "p_trans": 0.222598, "p_guess": 0.36377, "p_slip": 0.051413}, "310": {"p_init": 0.859349, "p_trans": 0.037896, "p_guess": 0.4999, "p_slip": 0.189962}, "734": {"p_init": 0.9778, "p_trans": 0.999844, "p_guess": 0.4999, "p_slip": 0.11585}, "312": {"p_init": 0.722725, "p_trans": 0.835525, "p_guess": 0.030168, "p_slip": 0.052145}, "534": {"p_init": 0.939452, "p_trans": 0.595817, "p_guess": 0.214942, "p_slip": 0.034286}, "636": {"p_init": 0.944529, "p_trans": 0.001318, "p_guess": 0.4999, "p_slip": 0.023974}, "657": {"p_init": 0.997511, "p_trans": 9.9e-05, "p_guess": 0.4999, "p_slip": 0.15366}, "658": {"p_init": 0.763665, "p_trans": 0.089421, "p_guess": 0.4999, "p_slip": 0.154805}, "287": {"p_init": 0.655477, "p_trans": 8.4e-05, "p_guess": 0.476524, "p_slip": 0.111937}, "48": {"p_init": 0.541706, "p_trans": 0.17505, "p_guess": 0.237453, "p_slip": 0.006292}, "52": {"p_init": 0.823171, "p_trans": 1e-06, "p_guess": 0.015842, "p_slip": 7e-06}, "17": {"p_init": 0.905228, "p_trans": 0.003177, "p_guess": 0.4999, "p_slip": 0.211224}, "314": {"p_init": 0.607533, "p_trans": 0.345763, "p_guess": 0.4999, "p_slip": 0.017013}, "594": {"p_init": 0.822937, "p_trans": 0.956069, "p_guess": 0.499875, "p_slip": 0.064065}, "593": {"p_init": 0.831614, "p_trans": 0.809332, "p_guess": 0.4999, "p_slip": 0.060497}, "595": {"p_init": 0.872687, "p_trans": 0.999799, "p_guess": 0.4999, "p_slip": 0.017528}, "565": {"p_init": 0.850576, "p_trans": 0.690573, "p_guess": 0.4999, "p_slip": 0.01507}, "506": {"p_init": 0.988207, "p_trans": 9e-06, "p_guess": 0.4999, "p_slip": 0.044455}, "548": {"p_init": 0.76885, "p_trans": 0.999487, "p_guess": 0.4999, "p_slip": 0.136815}, "685": {"p_init": 0.244356, "p_trans": 0.189976, "p_guess": 0.099886, "p_slip": 0.029868}, "504": {"p_init": 0.304765, "p_trans": 0.810798, "p_guess": 0.160083, "p_slip": 0.003146}, "333": {"p_init": 0.1, "p_trans": 1e-06, "p_guess": 1e-06, "p_slip": 1e-06}, "111": {"p_init": 0.732635, "p_trans": 0.999737, "p_guess": 0.4999, "p_slip": 0.142735}, "84": {"p_init": 0.715749, "p_trans": 0.029524, "p_guess": 0.433386, "p_slip": 0.106339}, "489": {"p_init": 0.751426, "p_trans": 0.245592, "p_guess": 0.4999, "p_slip": 0.053073}, "656": {"p_init": 0.908702, "p_trans": 0.031627, "p_guess": 0.4999, "p_slip": 0.159042}, "302": {"p_init": 0.867031, "p_trans": 0.035387, "p_guess": 0.4999, "p_slip": 0.101174}, "348": {"p_init": 0.84693, "p_trans": 0.000167, "p_guess": 0.4999, "p_slip": 0.032887}, "653": {"p_init": 0.162809, "p_trans": 0.546394, "p_guess": 0.481544, "p_slip": 0.018947}, "689": {"p_init": 0.198966, "p_trans": 0.945216, "p_guess": 0.187961, "p_slip": 0.000555}, "443": {"p_init": 0.877924, "p_trans": 0.094576, "p_guess": 0.4999, "p_slip": 0.067792}, "245": {"p_init": 0.515736, "p_trans": 0.998042, "p_guess": 0.4999, "p_slip": 0.14485}, "1": {"p_init": 0.510133, "p_trans": 0.35226, "p_guess": 0.4999, "p_slip": 0.030321}, "418": {"p_init": 0.677397, "p_trans": 0.44888, "p_guess": 0.270582, "p_slip": 0.003328}, "419": {"p_init": 0.940655, "p_trans": 0.011334, "p_guess": 0.4999, "p_slip": 0.113993}, "126": {"p_init": 0.588087, "p_trans": 0.933205, "p_guess": 0.4999, "p_slip": 0.130753}, "334": {"p_init": 0.986938, "p_trans": 0.999775, "p_guess": 0.4999, "p_slip": 0.006394}, "425": {"p_init": 0.75579, "p_trans": 0.05425, "p_guess": 0.4999, "p_slip": 0.130269}, "424": {"p_init": 0.908435, "p_trans": 0.000263, "p_guess": 0.4999, "p_slip": 0.104124}, "426": {"p_init": 0.681612, "p_trans": 0.347527, "p_guess": 0.304584, "p_slip": 1.6e-05}, "625": {"p_init": 0.531924, "p_trans": 0.642329, "p_guess": 0.356652, "p_slip": 0.012311}, "581": {"p_init": 0.839573, "p_trans": 2e-06, "p_guess": 0.4999, "p_slip": 0.361426}, "695": {"p_init": 0.941654, "p_trans": 1e-06, "p_guess": 0.4999, "p_slip": 0.198111}, "696": {"p_init": 0.672482, "p_trans": 0.604647, "p_guess": 0.4999, "p_slip": 0.00271}, "698": {"p_init": 0.952976, "p_trans": 0.002013, "p_guess": 0.481712, "p_slip": 0.100246}, "679": {"p_init": 0.9999, "p_trans": 0.9544, "p_guess": 0.4999, "p_slip": 0.028022}, "545": {"p_init": 0.710501, "p_trans": 0.264772, "p_guess": 0.4999, "p_slip": 0.160211}, "438": {"p_init": 0.736479, "p_trans": 0.118019, "p_guess": 0.4999, "p_slip": 0.099}, "439": {"p_init": 0.736479, "p_trans": 0.118019, "p_guess": 0.4999, "p_slip": 0.099}, "441": {"p_init": 0.840614, "p_trans": 0.163844, "p_guess": 0.377054, "p_slip": 0.129811}, "654": {"p_init": 0.842446, "p_trans": 1e-06, "p_guess": 0.4999, "p_slip": 0.094783}, "89": {"p_init": 0.726685, "p_trans": 0.11791, "p_guess": 0.063273, "p_slip": 0.000247}, "305": {"p_init": 0.164844, "p_trans": 0.620282, "p_guess": 0.207992, "p_slip": 0.031591}, "515": {"p_init": 0.383102, "p_trans": 0.333309, "p_guess": 0.322409, "p_slip": 0.043676}, "498": {"p_init": 0.687329, "p_trans": 0.178236, "p_guess": 0.4999, "p_slip": 0.230014}, "293": {"p_init": 0.402702, "p_trans": 0.001787, "p_guess": 0.346143, "p_slip": 0.151098}, "503": {"p_init": 0.999823, "p_trans": 0.996958, "p_guess": 0.4999, "p_slip": 0.078093}, "775": {"p_init": 0.9999, "p_trans": 0.9999, "p_guess": 0.4999, "p_slip": 1e-06}, "398": {"p_init": 0.834904, "p_trans": 1e-06, "p_guess": 0.4999, "p_slip": 0.162695}, "357": {"p_init": 0.372844, "p_trans": 0.238429, "p_guess": 0.4999, "p_slip": 0.084706}, "645": {"p_init": 0.634455, "p_trans": 0.040242, "p_guess": 0.4999, "p_slip": 0.404468}, "415": {"p_init": 0.48259, "p_trans": 0.000637, "p_guess": 0.29948, "p_slip": 0.040348}, "416": {"p_init": 0.337759, "p_trans": 0.05721, "p_guess": 0.234826, "p_slip": 0.058658}, "417": {"p_init": 0.337759, "p_trans": 0.05721, "p_guess": 0.234826, "p_slip": 0.058658}, "473": {"p_init": 0.838422, "p_trans": 3.6e-05, "p_guess": 0.4999, "p_slip": 0.00405}, "474": {"p_init": 0.9999, "p_trans": 0.035346, "p_guess": 0.4999, "p_slip": 0.058802}, "299": {"p_init": 0.441363, "p_trans": 0.804176, "p_guess": 0.4999, "p_slip": 0.063497}, "521": {"p_init": 0.823094, "p_trans": 0.025126, "p_guess": 0.20516, "p_slip": 0.090407}, "450": {"p_init": 0.847981, "p_trans": 0.313453, "p_guess": 0.158565, "p_slip": 0.070497}, "547": {"p_init": 0.800043, "p_trans": 1e-06, "p_guess": 0.239309, "p_slip": 0.002064}, "549": {"p_init": 0.9999, "p_trans": 0.991668, "p_guess": 0.4999, "p_slip": 0.027655}, "573": {"p_init": 0.999807, "p_trans": 4e-06, "p_guess": 0.4999, "p_slip": 0.0074}, "319": {"p_init": 0.9999, "p_trans": 0.03261, "p_guess": 0.4999, "p_slip": 0.063137}, "576": {"p_init": 0.771014, "p_trans": 0.022508, "p_guess": 4e-05, "p_slip": 0.075284}, "632": {"p_init": 0.434693, "p_trans": 0.692286, "p_guess": 0.000175, "p_slip": 1e-06}, "631": {"p_init": 0.240724, "p_trans": 0.889455, "p_guess": 0.41607, "p_slip": 0.045885}, "633": {"p_init": 0.264532, "p_trans": 0.997077, "p_guess": 0.334938, "p_slip": 0.116532}, "564": {"p_init": 0.255218, "p_trans": 0.058623, "p_guess": 0.4999, "p_slip": 0.437463}, "720": {"p_init": 0.714377, "p_trans": 0.249788, "p_guess": 0.092175, "p_slip": 0.039389}, "274": {"p_init": 0.839963, "p_trans": 0.000114, "p_guess": 0.278365, "p_slip": 0.001411}, "780": {"p_init": 0.911761, "p_trans": 1e-06, "p_guess": 0.4999, "p_slip": 0.300289}, "385": {"p_init": 0.875995, "p_trans": 0.417836, "p_guess": 0.4999, "p_slip": 0.056565}, "502": {"p_init": 0.201091, "p_trans": 0.541368, "p_guess": 0.493776, "p_slip": 0.0429}, "691": {"p_init": 0.431691, "p_trans": 0.028065, "p_guess": 0.4999, "p_slip": 0.248824}, "404": {"p_init": 0.73747, "p_trans": 0.016827, "p_guess": 0.4999, "p_slip": 0.12052}, "665": {"p_init": 0.614285, "p_trans": 0.349925, "p_guess": 0.40772, "p_slip": 0.005192}, "387": {"p_init": 0.872533, "p_trans": 0.142444, "p_guess": 0.270436, "p_slip": 0.045323}, "436": {"p_init": 0.532089, "p_trans": 0.721209, "p_guess": 0.236769, "p_slip": 0.003461}, "397": {"p_init": 0.661415, "p_trans": 1.7e-05, "p_guess": 0.4999, "p_slip": 0.040894}, "452": {"p_init": 0.969574, "p_trans": 0.163301, "p_guess": 0.4999, "p_slip": 0.074549}, "60": {"p_init": 0.965693, "p_trans": 1e-06, "p_guess": 0.000337, "p_slip": 0.094519}, "298": {"p_init": 0.457528, "p_trans": 0.306507, "p_guess": 0.130869, "p_slip": 0.010244}, "712": {"p_init": 0.08337, "p_trans": 0.682131, "p_guess": 4e-06, "p_slip": 0.000429}, "429": {"p_init": 0.000905, "p_trans": 0.772425, "p_guess": 0.423866, "p_slip": 0.105065}, "619": {"p_init": 0.999647, "p_trans": 1e-06, "p_guess": 0.4999, "p_slip": 0.142783}, "440": {"p_init": 0.57145, "p_trans": 0.76611, "p_guess": 0.4999, "p_slip": 0.002711}, "430": {"p_init": 0.483, "p_trans": 0.693693, "p_guess": 0.189135, "p_slip": 0.003779}, "517": {"p_init": 0.943217, "p_trans": 1e-06, "p_guess": 0.344742, "p_slip": 0.034627}, "651": {"p_init": 0.803625, "p_trans": 1e-06, "p_guess": 0.31968, "p_slip": 0.003442}, "449": {"p_init": 0.942578, "p_trans": 1e-06, "p_guess": 0.4999, "p_slip": 0.027994}, "476": {"p_init": 0.856171, "p_trans": 0.693547, "p_guess": 0.4999, "p_slip": 0.144757}, "461": {"p_init": 0.992061, "p_trans": 0.9999, "p_guess": 0.4999, "p_slip": 0.049531}, "683": {"p_init": 0.833333, "p_trans": 1e-06, "p_guess": 1e-06, "p_slip": 1e-06}, "598": {"p_init": 0.9999, "p_trans": 0.155842, "p_guess": 0.4999, "p_slip": 0.215675}, "537": {"p_init": 0.8838, "p_trans": 0.9999, "p_guess": 0.462167, "p_slip": 1e-06}, "522": {"p_init": 0.9999, "p_trans": 0.736624, "p_guess": 0.4999, "p_slip": 0.059688}, "705": {"p_init": 0.980865, "p_trans": 1.5e-05, "p_guess": 1e-06, "p_slip": 0.046147}, "457": {"p_init": 0.950439, "p_trans": 0.9999, "p_guess": 0.482696, "p_slip": 1e-06}, "520": {"p_init": 0.959457, "p_trans": 0.153062, "p_guess": 0.4999, "p_slip": 0.045217}, "529": {"p_init": 0.447661, "p_trans": 1e-06, "p_guess": 0.445021, "p_slip": 0.012779}, "822": {"p_init": 0.535783, "p_trans": 0.000184, "p_guess": 0.4999, "p_slip": 0.089712}, "823": {"p_init": 0.535783, "p_trans": 0.000184, "p_guess": 0.4999, "p_slip": 0.089712}, "824": {"p_init": 0.66741, "p_trans": 0.002359, "p_guess": 0.4999, "p_slip": 0.098844}, "827": {"p_init": 0.302116, "p_trans": 0.52076, "p_guess": 0.203752, "p_slip": 0.02248}, "523": {"p_init": 0.956224, "p_trans": 1e-06, "p_guess": 0.252819, "p_slip": 0.08758}, "332": {"p_init": 0.869541, "p_trans": 0.666633, "p_guess": 0.000217, "p_slip": 1e-06}}